aghasher/__init__.py
aghasher/core.py
aghasher/utils.py
aghasher/version.txt
aghasher-0.1.1.dist-info/LICENSE
aghasher-0.1.1.dist-info/METADATA
aghasher-0.1.1.dist-info/WHEEL
aghasher-0.1.1.dist-info/top_level.txt
aghasher-0.1.1.dist-info/RECORD
