Metadata-Version: 2.1
Name: aghasher
Version: 0.1.1
Summary: An implementation of Anchor Graph Hashing
Home-page: https://github.com/dstein64/aghasher
Author: Daniel Steinberg
Author-email: ds@dannyadam.com
License: MIT
Keywords: anchor-graph-hashing,hashing,locality-sensitive-hashing,machine-learning
Classifier: Development Status :: 4 - Beta
Classifier: Intended Audience :: Developers
Classifier: Intended Audience :: Science/Research
Classifier: Topic :: Scientific/Engineering
Classifier: Topic :: Scientific/Engineering :: Artificial Intelligence
Classifier: Topic :: Scientific/Engineering :: Information Analysis
Classifier: License :: OSI Approved :: MIT License
Classifier: Operating System :: Unix
Classifier: Operating System :: POSIX :: Linux
Classifier: Operating System :: MacOS
Classifier: Operating System :: Microsoft :: Windows
Classifier: Programming Language :: Python :: 3
Classifier: Programming Language :: Python :: 3.6
License-File: LICENSE
Requires-Dist: numpy
Requires-Dist: scipy
